sequential/sipo/sipo.v
module sipo #(parameter N=4)
            (input d, reset, clk, 
                output [N-1:0] dout);

            reg [N-1:0] q;

         always @(posedge clk, negedge reset) begin
             if(!reset)
                 q = {N{1'b0}};
             else

                 q = (q>>1);
                  q[N-1] = d;
            
         end
         assign dout = q;

endmodule

sequential/shift_reg/sipo/sipo_tb.v
module sipo_tb;

reg d, reset, clk;
wire [3:0] dout;

sipo #(.N(4)) dut (.d(d), .reset(reset), .clk(clk), .dout(dout));
always #5 clk=~clk;

initial begin
    $dumpfile("sipo.vcd");
    $dumpvars(0,sipo_tb);

    $monitor("At time =%0t-->| clk=%b, reset=%b, d=%b | dout=%b",$time, clk,reset,d,dout);

    reset=0;
    clk=0;
    d=0;

    @(posedge clk)
        reset=1;

     d=1;
     repeat(6) @(posedge clk);

     d=0;
     repeat(6) @(posedge clk);

     $finish;
 end 
 
 endmodule

sequential/sipo/sipo.vcd
$date
	Tue Apr  7 20:50:28 2026
$end
$version
	Icarus Verilog
$end
$timescale
	1s
$end
$scope module sipo_tb $end
$var wire 4 ! dout [3:0] $end
$var reg 1 " clk $end
$var reg 1 # d $end
$var reg 1 $ reset $end
$scope module dut $end
$var wire 1 " clk $end
$var wire 1 # d $end
$var wire 4 % dout [3:0] $end
$var wire 1 $ reset $end
$var parameter 32 & N $end
$var reg 4 ' q [3:0] $end
$upscope $end
$upscope $end
$enddefinitions $end
$comment Show the parameter values. $end
$dumpall
b100 &
$end
#0
$dumpvars
b0 '
b0 %
0$
0#
0"
b0 !
$end
#5
b1000 !
b1000 %
b1000 '
1#
1$
1"
#10
0"
#15
b1100 !
b1100 %
b1100 '
1"
#20
0"
#25
b1110 !
b1110 %
b1110 '
1"
#30
0"
#35
b1111 !
b1111 %
b1111 '
1"
#40
0"
#45
b1111 !
b1111 %
b1111 '
1"
#50
0"
#55
b1111 !
b1111 %
b1111 '
1"
#60
0"
#65
b111 !
b111 %
b111 '
0#
1"
#70
0"
#75
b11 !
b11 %
b11 '
1"
#80
0"
#85
b1 !
b1 %
b1 '
1"
#90
0"
#95
b0 !
b0 %
b0 '
1"
