arithmetic/oddeven_checker/oe_checker.v
module oe_checker (input [8:0] a, output odd, even);

assign odd = ^a;
assign even = ~^a;

endmodule

arithmetic/oddeven_checker/oe_checker_tb.v
module oe_checker_tb;
reg [8:0] a;
wire odd, even;
integer i;

oe_checker dut (.a(a), .odd(odd), .even(even));

initial begin
    $dumpfile ("oe_checker.vcd");
    $dumpvars (0, oe_checker_tb);

    $monitor("At time = %0t -- | a = %b | odd = %b, even = %b", $time, a,odd,even);

    for (i=-0; i<10; i=i+1) begin
    a = $urandom_range (0,7); #10;
    end
end
endmodule

arithmetic/oddeven_checker/oe_checker.vcd
$date
	Mon Mar 30 13:20:31 2026
$end
$version
	Icarus Verilog
$end
$timescale
	1s
$end
$scope module oe_checker_tb $end
$var wire 1 ! odd $end
$var wire 1 " even $end
$var reg 9 # a [8:0] $end
$var integer 32 $ i [31:0] $end
$scope module dut $end
$var wire 9 % a [8:0] $end
$var wire 1 ! odd $end
$var wire 1 " even $end
$upscope $end
$upscope $end
$enddefinitions $end
$comment Show the parameter values. $end
$dumpall
$end
#0
$dumpvars
b100 %
b0 $
b100 #
0"
1!
$end
#10
b10 #
b10 %
b1 $
#20
0!
1"
b0 #
b0 %
b10 $
#30
1!
0"
b1 #
b1 %
b11 $
#40
b100 #
b100 %
b100 $
#50
0!
1"
b110 #
b110 %
b101 $
#60
1!
0"
b1 #
b1 %
b110 $
#70
0!
1"
b0 #
b0 %
b111 $
#80
1!
0"
b100 #
b100 %
b1000 $
#90
b1001 $
#100
b1010 $
