arithmetic/CarryLookAheadAdder/cla.v
module cla (input [3:0] a,b, input cin, output [3:0] sum, output cout);
wire [3:0] p,g;
wire [4:0] c;
assign c[0] = cin;
genvar i;

generate

    for (i=0; i<4; i=i+1) begin: cla_block

    assign g[i] = a[i] & b[i];
    assign p[i] = a[i] ^ b[i];
    

    assign c[i+1] = g[i] | (p[i] & c[i]);
    
    assign sum[i] = p[i] ^ c[i];

end
endgenerate
assign cout = c[4];

endmodule

arithmetic/CarryLookAheadAdder/cla_tb.v
`timescale 1ns/1ps

module cla_tb;

reg [3:0] a,b;
reg cin;
wire [3:0] sum;
wire cout;
integer i;

cla uut (.a(a), .b(b), .cin(cin), .sum(sum), .cout(cout));

initial begin
    $dumpfile("cla.vcd");
    $dumpvars(0,cla_tb);

    $monitor ("At time t=%0t -- | a=%b, b=%b, cin=%b | sum=%b, cout-%b", $time, a,b,cin,sum,cout);

    a=0; b=0; cin=0; #10

    for (i=0; i<10; i=i+1) begin
    a = $urandom_range(0,15);
    b = $urandom_range(0,15);
    cin = $urandom_range(0,1);

    #10;
end
end
endmodule

arithmetic/CarryLookAheadAdder/cla.vcd
$date
	Tue Mar 31 10:10:23 2026
$end
$version
	Icarus Verilog
$end
$timescale
	1ps
$end
$scope module cla_tb $end
$var wire 4 ! sum [3:0] $end
$var wire 1 " cout $end
$var reg 4 # a [3:0] $end
$var reg 4 $ b [3:0] $end
$var reg 1 % cin $end
$var integer 32 & i [31:0] $end
$scope module uut $end
$var wire 4 ' a [3:0] $end
$var wire 4 ( b [3:0] $end
$var wire 1 % cin $end
$var wire 4 ) sum [3:0] $end
$var wire 4 * p [3:0] $end
$var wire 4 + g [3:0] $end
$var wire 1 " cout $end
$var wire 5 , c [4:0] $end
$scope begin cla_block[0] $end
$var parameter 2 - i $end
$upscope $end
$scope begin cla_block[1] $end
$var parameter 2 . i $end
$upscope $end
$scope begin cla_block[2] $end
$var parameter 3 / i $end
$upscope $end
$scope begin cla_block[3] $end
$var parameter 3 0 i $end
$upscope $end
$upscope $end
$upscope $end
$enddefinitions $end
$comment Show the parameter values. $end
$dumpall
b11 0
b10 /
b1 .
b0 -
$end
#0
$dumpvars
b0 ,
b0 +
b0 *
b0 )
b0 (
b0 '
bx &
0%
b0 $
b0 #
0"
b0 !
$end
#10000
b1101 !
b1101 )
b1101 *
b100 $
b100 (
b1001 #
b1001 '
b0 &
#20000
b1100 !
b1100 )
b1011 *
b111 ,
1%
b1000 $
b1000 (
b11 #
b11 '
b1 &
#30000
b100 !
b100 )
b11 *
b0 $
b0 (
b10 &
#40000
1"
b10111 ,
b1000 +
b1011 $
b1011 (
b1000 #
b1000 '
b11 &
#50000
b1100 !
b1100 )
b11111 ,
b1100 +
b1100 $
b1100 (
b1111 #
b1111 '
b100 &
#60000
0"
b1100 !
b1100 )
b0 *
b110 +
b1100 ,
0%
b110 $
b110 (
b110 #
b110 '
b101 &
#70000
1"
b11110 ,
b10 !
b10 )
b11 +
b1100 *
b11 $
b11 (
b1111 #
b1111 '
b110 &
#80000
b11000 ,
b1011 !
b1011 )
b1100 +
b11 *
b1111 $
b1111 (
b1100 #
b1100 '
b111 &
#90000
0"
b1110 !
b1110 )
b1 *
b110 +
b1111 ,
1%
b110 $
b110 (
b111 #
b111 '
b1000 &
#100000
b110 !
b110 )
b100 *
b1 +
b10 ,
0%
b1 $
b1 (
b101 #
b101 '
b1001 &
#110000
b1010 &
