arithmetic/rca/fa.v
module fa (input a,b, cin, output sum, output cout);


assign {cout,sum} = a+b+cin;

endmodule

arithmetic/rca/rca.v
module rca (input [3:0] a,b,
		input cin,
		output [3:0]sum, 
		output cout); 
wire [4:0] cinn;
genvar i;
assign cinn[0]=cin;
generate
	
for (i=0;i<4;i=i+1) begin: rca_block

fa fa_inst ( .a(a[i]), .b(b[i]), .cin(cinn[i]), .sum(sum[i]), .cout(cinn[i+1]) );

end
assign cout = cinn[4];		
endgenerate


endmodule

arithmetic/rca/rca_tb.v
`timescale 1ns/1ps

module rca_tb;

reg [3:0] a,b;
reg cin;
wire [3:0] sum;
wire cout;
wire [4:0]cinn;
integer i;

rca dut (.a(a),
	 .b(b),
	 .cin(cin),
	 .sum(sum),
	 .cout(cout));

 initial begin
	 $dumpfile ("ripple_adder.vcd");
	 $dumpvars (0,rca_tb);
 end

 initial begin
	 $monitor ("At time = %0t, a = %b, b=%b,cin=%b, cout = %b, sum = %b", $time, a,b,cin,cout,sum);
	 
	 a=0; b=0; cin=0;
	 #10;

	 for (i=0;i<10;i+=1) begin
		 a = $urandom_range (0,15);
		 b = $urandom_range (0,15);
		 cin = $urandom_range (0,1);

	 #10;
 end
 $finish;

end
endmodule

arithmetic/rca/ripple_adder.vcd
$date
	Sat Mar 28 12:48:55 2026
$end
$version
	Icarus Verilog
$end
$timescale
	1ps
$end
$scope module rca_tb $end
$var wire 4 ! sum [3:0] $end
$var wire 1 " cout $end
$var reg 4 # a [3:0] $end
$var reg 4 $ b [3:0] $end
$var reg 1 % cin $end
$var integer 32 & i [31:0] $end
$scope module dut $end
$var wire 4 ' a [3:0] $end
$var wire 4 ( b [3:0] $end
$var wire 1 % cin $end
$var wire 4 ) sum [3:0] $end
$var wire 1 " cout $end
$var wire 5 * cinn [4:0] $end
$scope begin rca_block[0] $end
$var parameter 2 + i $end
$scope module fa_inst $end
$var wire 1 , a $end
$var wire 1 - b $end
$var wire 1 . cin $end
$var wire 1 / sum $end
$var wire 1 0 cout $end
$upscope $end
$upscope $end
$scope begin rca_block[1] $end
$var parameter 2 1 i $end
$scope module fa_inst $end
$var wire 1 2 a $end
$var wire 1 3 b $end
$var wire 1 4 cin $end
$var wire 1 5 sum $end
$var wire 1 6 cout $end
$upscope $end
$upscope $end
$scope begin rca_block[2] $end
$var parameter 3 7 i $end
$scope module fa_inst $end
$var wire 1 8 a $end
$var wire 1 9 b $end
$var wire 1 : cin $end
$var wire 1 ; sum $end
$var wire 1 < cout $end
$upscope $end
$upscope $end
$scope begin rca_block[3] $end
$var parameter 3 = i $end
$scope module fa_inst $end
$var wire 1 > a $end
$var wire 1 ? b $end
$var wire 1 @ cin $end
$var wire 1 A sum $end
$var wire 1 B cout $end
$upscope $end
$upscope $end
$upscope $end
$upscope $end
$enddefinitions $end
$comment Show the parameter values. $end
$dumpall
b11 =
b10 7
b1 1
b0 +
$end
#0
$dumpvars
0B
0A
0@
0?
0>
0<
0;
0:
09
08
06
05
04
03
02
00
0/
0.
0-
0,
b0 *
b0 )
b0 (
b0 '
bx &
0%
b0 $
b0 #
0"
b0 !
$end
#10000
1;
1/
b1101 !
b1101 )
1A
19
1,
1>
b100 $
b100 (
b1001 #
b1001 '
b0 &
#20000
1:
16
14
0/
10
1;
b1100 !
b1100 )
05
1.
09
1?
12
0>
b111 *
1%
b1000 $
b1000 (
b11 #
b11 '
b1 &
#30000
b100 !
b100 )
0A
0?
b0 $
b0 (
b10 &
#40000
1"
b10111 *
1B
1-
13
1?
0,
02
1>
b1011 $
b1011 (
b1000 #
b1000 '
b11 &
#50000
b1100 !
b1100 )
1A
1@
b11111 *
1<
0-
03
19
1,
12
18
b1100 $
b1100 (
b1111 #
b1111 '
b100 &
#60000
0"
04
b1100 !
b1100 )
05
0B
00
0.
13
0?
0,
0>
b1100 *
0%
b110 $
b110 (
b110 #
b110 '
b101 &
#70000
15
14
1"
10
0;
b10 !
b10 )
0A
b11110 *
1B
1-
09
1,
1>
b11 $
b11 (
b1111 #
b1111 '
b110 &
#80000
0:
06
04
0;
1A
1/
b11000 *
00
b1011 !
b1011 )
15
19
1?
0,
02
b1111 $
b1111 (
b1100 #
b1100 '
b111 &
#90000
1;
0"
14
1:
0B
0/
10
b1110 !
b1110 )
15
16
1.
0-
0?
1,
12
0>
b1111 *
1%
b110 $
b110 (
b111 #
b111 '
b1000 &
#100000
0A
0@
0<
0:
06
b110 !
b110 )
1;
0.
1-
03
09
02
b10 *
0%
b1 $
b1 (
b101 #
b101 '
b1001 &
#110000
b1010 &
