combinational/dec_2to4_4to16/4to16Dec.v
module decoder_2to4(input [1:0] a,input en, output [3:0] out);

assign out = (en)? 4'b1<<a : 4'b0000;
endmodule


module decoder_4to16(input [3:0] a,input en, output [15:0] out);
wire [3:0] en_wire;

decoder_2to4 master (.a(a[3:2]),.out(en_wire),.en(en));

decoder_2to4 slave1 (.a(a[1:0]),.en(en_wire[0]),.out(out[3:0]));
decoder_2to4 slave2 (.a(a[1:0]),.en(en_wire[1]),.out(out[7:4]));
decoder_2to4 slave3 (.a(a[1:0]),.en(en_wire[2]),.out(out[11:8]));
decoder_2to4 slave4 (.a(a[1:0]),.en(en_wire[3]),.out(out[15:12]));

endmodule

combinational/dec_2to4_4to16/4to16_Dec_tb.v
module decoder_4to16_tb;

reg [3:0]a;
reg en;
output [15:0] out;
integer i;

decoder_4to16 dut(.a(a), .en(en), .out(out));

initial begin
    $dumpfile("4to6dec.vcd");
    $dumpvars(0, decoder_4to16_tb);

    $monitor ("At time = %0t -- | a=%b, en=%b | out = %b", $time, a,en,out);
    /*a=00; en=0; #10;
    a=01; en=1; #10;
    a=10; en=1; #10;
    a=11; en=1; #10;*/
    
   en = 1;
   
   for(i=0;i<16;i=i+1) begin
   
    a = i; #10;
      

end
$finish;
end
endmodule

combinational/dec_2to4_4to16/4to6dec.vcd
$date
	Wed Apr  1 13:44:50 2026
$end
$version
	Icarus Verilog
$end
$timescale
	1s
$end
$scope module decoder_4to16_tb $end
$var wire 16 ! out [15:0] $end
$var reg 4 " a [3:0] $end
$var reg 1 # en $end
$var integer 32 $ i [31:0] $end
$scope module dut $end
$var wire 4 % a [3:0] $end
$var wire 1 # en $end
$var wire 16 & out [15:0] $end
$var wire 4 ' en_wire [3:0] $end
$scope module master $end
$var wire 2 ( a [1:0] $end
$var wire 1 # en $end
$var wire 4 ) out [3:0] $end
$upscope $end
$scope module slave1 $end
$var wire 2 * a [1:0] $end
$var wire 1 + en $end
$var wire 4 , out [3:0] $end
$upscope $end
$scope module slave2 $end
$var wire 2 - a [1:0] $end
$var wire 1 . en $end
$var wire 4 / out [3:0] $end
$upscope $end
$scope module slave3 $end
$var wire 2 0 a [1:0] $end
$var wire 1 1 en $end
$var wire 4 2 out [3:0] $end
$upscope $end
$scope module slave4 $end
$var wire 2 3 a [1:0] $end
$var wire 1 4 en $end
$var wire 4 5 out [3:0] $end
$upscope $end
$upscope $end
$upscope $end
$enddefinitions $end
$comment Show the parameter values. $end
$dumpall
$end
#0
$dumpvars
b0 5
04
b0 3
b0 2
01
b0 0
b0 /
0.
b0 -
b1 ,
1+
b0 *
b1 )
b0 (
b1 '
b1 &
b0 %
b0 $
1#
b0 "
b1 !
$end
#10
b10 !
b10 &
b10 ,
b1 *
b1 -
b1 0
b1 3
b1 "
b1 %
b1 $
#20
b100 !
b100 &
b100 ,
b10 *
b10 -
b10 0
b10 3
b10 "
b10 %
b10 $
#30
b1000 !
b1000 &
b1000 ,
b11 *
b11 -
b11 0
b11 3
b11 "
b11 %
b11 $
#40
b1 /
1.
0+
b10 '
b10 )
b10000 !
b10000 &
b0 ,
b1 (
b0 *
b0 -
b0 0
b0 3
b100 "
b100 %
b100 $
#50
b100000 !
b100000 &
b10 /
b1 *
b1 -
b1 0
b1 3
b101 "
b101 %
b101 $
#60
b1000000 !
b1000000 &
b100 /
b10 *
b10 -
b10 0
b10 3
b110 "
b110 %
b110 $
#70
b10000000 !
b10000000 &
b1000 /
b11 *
b11 -
b11 0
b11 3
b111 "
b111 %
b111 $
#80
b1 2
11
0.
b100 '
b100 )
b100000000 !
b100000000 &
b0 /
b10 (
b0 *
b0 -
b0 0
b0 3
b1000 "
b1000 %
b1000 $
#90
b1000000000 !
b1000000000 &
b10 2
b1 *
b1 -
b1 0
b1 3
b1001 "
b1001 %
b1001 $
#100
b10000000000 !
b10000000000 &
b100 2
b10 *
b10 -
b10 0
b10 3
b1010 "
b1010 %
b1010 $
#110
b100000000000 !
b100000000000 &
b1000 2
b11 *
b11 -
b11 0
b11 3
b1011 "
b1011 %
b1011 $
#120
b1 5
14
01
b1000 '
b1000 )
b1000000000000 !
b1000000000000 &
b0 2
b11 (
b0 *
b0 -
b0 0
b0 3
b1100 "
b1100 %
b1100 $
#130
b10000000000000 !
b10000000000000 &
b10 5
b1 *
b1 -
b1 0
b1 3
b1101 "
b1101 %
b1101 $
#140
b100000000000000 !
b100000000000000 &
b100 5
b10 *
b10 -
b10 0
b10 3
b1110 "
b1110 %
b1110 $
#150
b1000000000000000 !
b1000000000000000 &
b1000 5
b11 *
b11 -
b11 0
b11 3
b1111 "
b1111 %
b1111 $
#160
b10000 $
