sequential/Dff/Dff_reset/Dff_reset.v
module D_reset (input d,clk,reset, output reg q,output qbar);
assign qbar = ~q;
always @(posedge clk) begin
    if(reset)
        q <= 1'b0;
    else
        q <= d;
end
endmodule

module D_reset_async (input d,clk,reset, output reg q,output qbar);
assign qbar = ~q;
always @(posedge clk, posedge reset) begin
    if (reset)
        q <= 1'b0;
    else
        q <= d;
end
endmodule

module d_r (input d,clk,reset, output Q_syn, QB_syn, Q_Asyn, QB_Asyn);

D_reset d1 (.d(d), .clk(clk), .reset(reset), .q(Q_syn), .qbar(QB_syn));
D_reset_async d2 (.d(d), .clk(clk), .reset(reset), .q(Q_Asyn), .qbar(QB_Asyn));

endmodule

sequential/Dff/Dff_reset/D_reset_tb.v
module D_reset_tb;

reg d,clk, reset;
wire Q_syn, QB_syn, Q_Asyn, QB_Asyn;

d_r dut (.d(d), .clk(clk), .reset(reset), .Q_syn(Q_syn), .QB_syn(QB_syn),.Q_Asyn(Q_Asyn),.QB_Asyn(QB_Asyn));

initial clk = 0;
always #5 clk=~clk;

initial begin 
    $dumpfile("d_r.vcd");
    $dumpvars(0,D_reset_tb);

    $monitor("At time=%0t-->| clk=%b, d=%b, reset=%b| Q_Sync=%b, QB_Sync=%b, Q_Async=%b,QB_Async=%b", $time,clk,d,reset,Q_syn,QB_syn,Q_Asyn,QB_Asyn);

    repeat(8) begin
       @(negedge clk); 
        d=$random;
        reset=$random;
    end
    #10; $finish;
end 

endmodule

sequential/Dff/Dff_reset/d_r.vcd
$date
	Mon Apr  6 16:49:55 2026
$end
$version
	Icarus Verilog
$end
$timescale
	1s
$end
$scope module D_reset_tb $end
$var wire 1 ! Q_syn $end
$var wire 1 " Q_Asyn $end
$var wire 1 # QB_syn $end
$var wire 1 $ QB_Asyn $end
$var reg 1 % clk $end
$var reg 1 & d $end
$var reg 1 ' reset $end
$scope module dut $end
$var wire 1 % clk $end
$var wire 1 & d $end
$var wire 1 ' reset $end
$var wire 1 ! Q_syn $end
$var wire 1 " Q_Asyn $end
$var wire 1 # QB_syn $end
$var wire 1 $ QB_Asyn $end
$scope module d1 $end
$var wire 1 % clk $end
$var wire 1 & d $end
$var wire 1 # qbar $end
$var wire 1 ' reset $end
$var reg 1 ! q $end
$upscope $end
$scope module d2 $end
$var wire 1 % clk $end
$var wire 1 & d $end
$var wire 1 $ qbar $end
$var wire 1 ' reset $end
$var reg 1 " q $end
$upscope $end
$upscope $end
$upscope $end
$enddefinitions $end
$comment Show the parameter values. $end
$dumpall
$end
#0
$dumpvars
x'
x&
0%
x$
x#
x"
x!
$end
#5
1%
#10
1$
0"
1'
0&
0%
#15
1#
0!
1%
#20
1&
0%
#25
1%
#30
0%
#35
1%
#40
0'
0%
#45
0#
0$
1!
1"
1%
#50
1$
0"
1'
0%
#55
1#
0!
1%
#60
0&
0%
#65
1%
#70
0'
1&
0%
#75
0#
0$
1!
1"
1%
