sequential/Dff/Dff_reset/Dff_reset.v
module D_reset (input d,clk,reset, output reg q,qbar);

always @(posedge clk) begin
    if(reset)
        {q,qbar} <= 2'b01;
    else
        {q, qbar} <= {d,~d};
end
endmodule

sequential/Dff/Dff_reset/D_reset_tb.v
module D_reset_tb;

reg d,clk, reset;
wire q, qbar;

D_reset dut (.d(d), .clk(clk), .reset(reset), .q(q), .qbar(qbar));

initial clk = 0;
always #5 clk=~clk;

initial begin 
    $dumpfile("d_r.vcd");
    $dumpvars(0,D_reset_tb);

    $monitor("At time=%0t-->| clk=%b, d=%b, reset=%b| q=%b, qbar=%b", $time,clk,d,reset,q,qbar);

    repeat(10) begin
        @(negedge clk);
        d=$random;
        reset=$random;
    end
    #10; $finish;
end
endmodule

sequential/Dff/Dff_reset/d_r.vcd
$date
	Mon Apr  6 15:33:39 2026
$end
$version
	Icarus Verilog
$end
$timescale
	1s
$end
$scope module D_reset_tb $end
$var wire 1 ! qbar $end
$var wire 1 " q $end
$var reg 1 # clk $end
$var reg 1 $ d $end
$var reg 1 % reset $end
$scope module dut $end
$var wire 1 # clk $end
$var wire 1 $ d $end
$var wire 1 % reset $end
$var reg 1 " q $end
$var reg 1 ! qbar $end
$upscope $end
$upscope $end
$enddefinitions $end
$comment Show the parameter values. $end
$dumpall
$end
#0
$dumpvars
x%
x$
0#
x"
x!
$end
#5
1#
#10
1%
0$
0#
#15
0"
1!
1#
#20
1$
0#
#25
1#
#30
0#
#35
1#
#40
0%
0#
#45
1"
0!
1#
#50
1%
0#
#55
0"
1!
1#
#60
0$
0#
#65
1#
#70
0%
1$
0#
#75
1"
0!
1#
#80
0#
#85
1#
#90
0#
#95
1#
#100
1%
0#
#105
0"
1!
1#
