sequential/register/register.v
module register #(parameter N = 4)
                    (input [N-1:0] d,
                     input en, clk, reset,
                     output reg [N-1:0] q);
                 
        always @(posedge clk) begin
            if(reset)
                q <= 4'b0;
            else if (en)
                q <= d;
            
        end
 endmodule

sequential/shift_reg/pipo/register_tb.v
module register_tb;

reg [3:0] d;
reg en, clk, reset;
wire [3:0] q;

register dut (.d(d), .en(en), .clk(clk), .reset(reset), .q(q));
always #5 clk = ~clk;

initial begin
    $dumpfile("register.vcd");
    $dumpvars(0,register_tb);

    $monitor("At time=%0t-->| d=%b, en=%b, clk=%b, reset=%b | q=%b", $time, d,en,clk,reset,q);
    
    clk=0;
    en=0;
    reset = 1;
    d = 0;

    #10; reset = 0;

    repeat (8) begin
        @(negedge clk);
        d = $random; 
        en = $random;
        
    end
#20; $finish;
end
endmodule

sequential/pipo/register.vcd
$date
	Tue Apr  7 13:41:40 2026
$end
$version
	Icarus Verilog
$end
$timescale
	1s
$end
$scope module register_tb $end
$var wire 4 ! q [3:0] $end
$var reg 1 " clk $end
$var reg 4 # d [3:0] $end
$var reg 1 $ en $end
$var reg 1 % reset $end
$scope module dut $end
$var wire 1 " clk $end
$var wire 4 & d [3:0] $end
$var wire 1 $ en $end
$var wire 1 % reset $end
$var parameter 32 ' N $end
$var reg 4 ( q [3:0] $end
$upscope $end
$upscope $end
$enddefinitions $end
$comment Show the parameter values. $end
$dumpall
b100 '
$end
#0
$dumpvars
bx (
b0 &
1%
0$
b0 #
0"
bx !
$end
#5
b0 !
b0 (
1"
#10
1$
b100 #
b100 &
0"
0%
#15
b100 !
b100 (
1"
#20
b1001 #
b1001 &
0"
#25
b1001 !
b1001 (
1"
#30
b1101 #
b1101 &
0"
#35
b1101 !
b1101 (
1"
#40
0$
b101 #
b101 &
0"
#45
1"
#50
1$
b1 #
b1 &
0"
#55
b1 !
b1 (
1"
#60
b110 #
b110 &
0"
#65
b110 !
b110 (
1"
#70
0$
b1101 #
b1101 &
0"
#75
1"
#80
b1001 #
b1001 &
0"
