sequential/shift_reg/uni_reg/uni_reg.v
module uni_reg #(parameter N=4)               

                 (input [N-1:0] pin,
                  input sin, clk, reset,
                  input [1:0] mode,
                  output [N-1:0] dout );
             
          reg [N-1:0] q;

         always @(posedge clk, negedge reset) begin
                
             if (!reset) begin
                 q <= {N{1'b0}};
                end

                else if (mode == 2'b01) begin
                 q <= (q>>1);
                 q[N-1] <= sin;
                end

                else if (mode == 2'b10) begin
                 q <= (q<<1);
                 q[0] <= sin;
                end

                else if (mode == 2'b11) begin

                   q <= pin;
                end 
      end
          assign dout = q;

          endmodule

sequential/shift_reg/uni_reg/uni_reg_tb.v
module uni_reg_tb;

reg [3:0] pin;
reg sin, clk, reset;
reg [1:0] mode;
wire [3:0] dout;
integer i;

uni_reg #(.N(4)) dut (.pin(pin), .sin(sin), .clk(clk), .reset(reset), .mode(mode), .dout(dout));

always #5 clk = ~clk;

initial begin 
    $dumpfile ("uni_reg.vcd");
    $dumpvars (0,uni_reg_tb);

    $monitor ("AT time=%0t-->| clk=%b, reset=%b, mode=%b, parallel_in=%b, serial_in=%b | dout=%b",$time,clk,reset,mode,pin,sin,dout);

    sin=0; clk=0; mode=0;
    reset = 0;

    @(posedge clk) reset = 1;

    for(i=0; i<4; i++) begin
        mode =i;

      if (mode == 2'b11) pin = $random;

      else 
          sin = $random; repeat (4)@(negedge clk);
  end
  #20; $finish;
 end
endmodule

sequential/shift_reg/uni_reg/uni_reg.vcd
$date
	Wed Apr  8 21:08:24 2026
$end
$version
	Icarus Verilog
$end
$timescale
	1s
$end
$scope module uni_reg_tb $end
$var wire 4 ! dout [3:0] $end
$var reg 1 " clk $end
$var reg 2 # mode [1:0] $end
$var reg 4 $ pin [3:0] $end
$var reg 1 % reset $end
$var reg 1 & sin $end
$var integer 32 ' i [31:0] $end
$scope module dut $end
$var wire 1 " clk $end
$var wire 4 ( dout [3:0] $end
$var wire 2 ) mode [1:0] $end
$var wire 4 * pin [3:0] $end
$var wire 1 % reset $end
$var wire 1 & sin $end
$var parameter 32 + N $end
$var reg 4 , q [3:0] $end
$upscope $end
$upscope $end
$enddefinitions $end
$comment Show the parameter values. $end
$dumpall
b100 +
$end
#0
$dumpvars
b0 ,
bx *
b0 )
b0 (
bx '
0&
0%
bx $
b0 #
0"
b0 !
$end
#5
b0 '
1%
1"
#10
0"
#15
1"
#20
0"
#25
1"
#30
0"
#35
1"
#40
1&
b1 #
b1 )
b1 '
0"
#45
b1000 !
b1000 (
b1000 ,
1"
#50
0"
#55
b1100 !
b1100 (
b1100 ,
1"
#60
0"
#65
b1110 !
b1110 (
b1110 ,
1"
#70
0"
#75
b1111 !
b1111 (
b1111 ,
1"
#80
b10 #
b10 )
b10 '
0"
#85
b1111 !
b1111 (
b1111 ,
1"
#90
0"
#95
b1111 !
b1111 (
b1111 ,
1"
#100
0"
#105
b1111 !
b1111 (
b1111 ,
1"
#110
0"
#115
b1111 !
b1111 (
b1111 ,
1"
#120
b11 $
b11 *
b11 #
b11 )
b11 '
0"
#125
b11 !
b11 (
b11 ,
1"
#130
0"
#135
1"
#140
0"
#145
1"
#150
0"
#155
1"
#160
b100 '
0"
