sequential/shift_reg/siso/shift_reg.v
module shift_reg #(parameter N=4)
                    (input d,reset, clk, mode,
                     output  dout);

            reg [N-1:0] q;
                 
           always @(posedge clk, negedge reset) begin
               if (!reset)
                   q <= {N{1'b0}};
               else if (mode) begin
                   q <= (q>>1) | (d<<q[N-1]) & 1'b1;
                end
                else begin
                   q <= (q<<1) | d & 1'b1;
               end
              end
                
                assign dout = mode ? q[0] : q[N-1];

               endmodule

sequential/shift_reg/siso/shift_reg_tb.v
module shift_reg_tb;

reg d, reset, clk, mode;
wire dout;

shift_reg #(.N(4)) dut (.d(d), .reset(reset), .clk(clk), .mode(mode), .dout(dout));
always #5 clk=~clk;

initial begin
    $dumpfile("shift_reg.vcd");
    $dumpvars(0,shift_reg_tb);
    
    $monitor("At time t=%0t-->| clk=%b, reset=%b, mode=%b, d=%b | dout=%b", $time,clk,reset,mode,d,dout);
    clk=0;
    reset = 0;
    d=0;
    mode=0;
    
    @(posedge clk);
     reset = 1;


     d =1;
     mode=0;
    repeat(6)@(posedge clk);
        
      d =0;
     mode=1;
    repeat(6)@(posedge clk);

       
        
     $finish;
    end
endmodule

sequential/shift_reg/siso/shift_reg.vcd
$date
	Thu Apr  9 11:33:21 2026
$end
$version
	Icarus Verilog
$end
$timescale
	1s
$end
$scope module shift_reg_tb $end
$var wire 1 ! dout $end
$var reg 1 " clk $end
$var reg 1 # d $end
$var reg 1 $ mode $end
$var reg 1 % reset $end
$scope module dut $end
$var wire 1 " clk $end
$var wire 1 # d $end
$var wire 1 $ mode $end
$var wire 1 % reset $end
$var wire 1 ! dout $end
$var parameter 32 & N $end
$var reg 4 ' q [3:0] $end
$upscope $end
$upscope $end
$enddefinitions $end
$comment Show the parameter values. $end
$dumpall
b100 &
$end
#0
$dumpvars
b0 '
0%
0$
0#
0"
0!
$end
#5
b1 '
1#
1%
1"
#10
0"
#15
b11 '
1"
#20
0"
#25
b111 '
1"
#30
0"
#35
1!
b1111 '
1"
#40
0"
#45
1"
#50
0"
#55
1"
#60
0"
#65
b111 '
1$
0#
1"
#70
0"
#75
b11 '
1"
#80
0"
#85
b1 '
1"
#90
0"
#95
0!
b0 '
1"
