combinational/encoder/encoder.v
module encoder #(parameter N=8, parameter Y = $clog2 (N))
                 (   input [N-1:0] d,
                    output reg [Y-1:0] a
                 );

                 integer i;
                 
                 always @(*) begin
                     a = 0;
                     for (i=0; i<N; i=i+1) begin
                         if(d[i]) a = i;

                     end
             end
             endmodule

combinational/encoder/encoder_tb.v
module encoder_tb;

reg [7:0] d;
wire [2:0] a;

encoder #(.N(8)) dut (.d(d), .a(a));

initial begin 
    $dumpfile("encoder.vcd");
    $dumpvars(0, encoder_tb);

    $monitor ("At time =%0t --> | d=%b | a=%b", $time, d,a);

            repeat (8) begin
            d = $random; #10;
            end
        end
        endmodule

combinational/encoder/encoder.vcd
$date
	Sat Apr  4 14:35:45 2026
$end
$version
	Icarus Verilog
$end
$timescale
	1s
$end
$scope module encoder_tb $end
$var wire 3 ! a [2:0] $end
$var reg 8 " d [7:0] $end
$scope module dut $end
$var wire 8 # d [7:0] $end
$var parameter 32 $ N $end
$var parameter 32 % Y $end
$var reg 3 & a [2:0] $end
$var integer 32 ' i [31:0] $end
$upscope $end
$upscope $end
$enddefinitions $end
$comment Show the parameter values. $end
$dumpall
b11 %
b1000 $
$end
#0
$dumpvars
b1000 '
b101 &
b100100 #
b100100 "
b101 !
$end
#10
b1000 '
b111 !
b111 &
b10000001 "
b10000001 #
#20
b1000 '
b11 !
b11 &
b1001 "
b1001 #
#30
b1000 '
b110 !
b110 &
b1100011 "
b1100011 #
#40
b1000 '
b11 !
b11 &
b1101 "
b1101 #
#50
b1000 '
b111 !
b111 &
b10001101 "
b10001101 #
#60
b1000 '
b110 !
b110 &
b1100101 "
b1100101 #
#70
b1000 '
b100 !
b100 &
b10010 "
b10010 #
