combinational/mux (2x1, 4x1 using 2x1, 16x1 using 4x1)/mux.v
module mux_2x1_gate (input [1:0] a, input s, output y);

wire w1,w2,w3;

not (w1,s);
and (w2,w1,a[0]);
and (w3,s,a[1]);

or (y,w2,w3);

endmodule

module mux_2x1_df (input [1:0] a, input s, output y);

wire w1,w2,w3;

assign w1 = ~s;
assign w2 = w1 & a[0];
assign w3 = s & a[1];

assign y = w2 | w3;

endmodule

module mux_2x1_bh (input [1:0] a, input s, output reg y);


always @(*) begin
if (s)
    y=a[1];
else
    y=a[0];

end

endmodule
     
module mux_all (input [1:0] a, input s, output y_ga, y_da, y_be);

mux_2x1_gate m1 (.a(a[1:0]),.s(s),.y(y_ga));
mux_2x1_df m2 (.a(a[1:0]),.s(s),.y(y_da));
mux_2x1_bh m3 (.a(a[1:0]),.s(s),.y(y_be));

endmodule

combinational/mux (2x1, 4x1 using 2x1, 16x1 using 4x1)/4x1mux.v
module mux4x1 (input [3:0]a, input [1:0]s, output y);
wire [1:0] en; 

mux_2x1_bh m1 (.a(a[1:0]), .s(s[0]), .y(en[0]));
mux_2x1_bh m2 (.a(a[3:2]), .s(s[0]), .y(en[1]));

mux_2x1_bh m3 (.a(en[1:0]), .s(s[1]), .y(y));

endmodule

combinational/mux (2x1, 4x1 using 2x1, 16x1 using 4x1)/4x1mux_tb.v
module mux4x1tb;

reg [3:0] a;
reg [1:0] s;
wire y;
integer i;

mux4x1 dut (.a(a), .s(s),.y(y));

initial begin
    $dumpfile ("4x1mux.vcd");
    $dumpvars (0, mux4x1tb);

    $monitor ("At time t=%0t --| a=%b, s=%b | y=%b", $time, a,s,y);

    a=0; s=0; #10;
    
    repeat(3) begin
    a = $random; #10;
    for (i=0;i<4;i=i+1) begin 
        s = i; 
    #10;
    end
    end
end
endmodule

combinational/mux (2x1, 4x1 using 2x1, 16x1 using 4x1)/4x1mux.vcd
$date
	Thu Apr  2 11:58:42 2026
$end
$version
	Icarus Verilog
$end
$timescale
	1s
$end
$scope module mux4x1tb $end
$var wire 1 ! y $end
$var reg 4 " a [3:0] $end
$var reg 2 # s [1:0] $end
$var integer 32 $ i [31:0] $end
$scope module dut $end
$var wire 4 % a [3:0] $end
$var wire 2 & s [1:0] $end
$var wire 1 ! y $end
$var wire 2 ' en [1:0] $end
$scope module m1 $end
$var wire 2 ( a [1:0] $end
$var wire 1 ) s $end
$var reg 1 * y $end
$upscope $end
$scope module m2 $end
$var wire 2 + a [1:0] $end
$var wire 1 , s $end
$var reg 1 - y $end
$upscope $end
$scope module m3 $end
$var wire 2 . a [1:0] $end
$var wire 1 / s $end
$var reg 1 ! y $end
$upscope $end
$upscope $end
$upscope $end
$enddefinitions $end
$comment Show the parameter values. $end
$dumpall
$end
#0
$dumpvars
0/
b0 .
0-
0,
b0 +
0*
0)
b0 (
b0 '
b0 &
b0 %
bx $
b0 #
b0 "
0!
$end
#10
b10 '
b10 .
1-
b1 +
b100 "
b100 %
#20
b0 $
#30
b0 '
b0 .
0-
1)
1,
b1 #
b1 &
b1 $
#40
1!
b10 '
b10 .
1-
0)
0,
1/
b10 #
b10 &
b10 $
#50
0!
b0 '
b0 .
0-
1)
1,
b11 #
b11 &
b11 $
#60
b1 (
b0 +
b1 "
b1 %
b100 $
#70
1!
b1 '
b1 .
1*
0)
0,
0/
b0 #
b0 &
b0 $
#80
0!
b0 '
b0 .
0*
1)
1,
b1 #
b1 &
b1 $
#90
b1 '
b1 .
1*
0)
0,
1/
b10 #
b10 &
b10 $
#100
b0 '
b0 .
0*
1)
1,
b11 #
b11 &
b11 $
#110
1!
b10 '
b10 .
1-
b10 +
b1001 "
b1001 %
b100 $
#120
1*
b1 '
b1 .
0-
1!
0)
0,
0/
b0 #
b0 &
b0 $
#130
0!
0*
b10 '
b10 .
1-
1)
1,
b1 #
b1 &
b1 $
#140
1*
b1 '
b1 .
0-
0!
0)
0,
1/
b10 #
b10 &
b10 $
#150
1!
0*
b10 '
b10 .
1-
1)
1,
b11 #
b11 &
b11 $
#160
b100 $
