combinational/mux/mux.v
module mux_2x1_gate (input a,b,s, output y);

wire w1,w2,w3;

not (w1,s);
and (w2,w1,a);
and (w3,s,b);

or (y,w2,w3);

endmodule

module mux_2x1_df (input a,b,s, output y);

wire w1,w2,w3;

assign w1 = ~s;
assign w2 = w1 & a;
assign w3 = s & b;

assign y = w2 | w3;

endmodule

module mux_2x1_bh (input a,b,s, output reg y);

reg w1, w2, w3;


always @(*) begin
    w1 = ~s;
    w2 = w1 & a;
    w3 = s & b;

    y = w2 | w3;
end
endmodule
     
module mux_all (input a,b,s, output y_ga, y_da, y_be);

mux_2x1_gate m1 (.a(a),.b(b),.s(s),.y(y_ga));
mux_2x1_df m2 (.a(a),.b(b),.s(s),.y(y_da));
mux_2x1_bh m3 (.a(a),.b(b),.s(s),.y(y_be));

endmodule

combinational/mux (2x1, 4x1 using 2x1, 16x1 using 4x1)/mux_tb.v
module mux_2x1_tb;

reg a,b,s;
wire y_ga;
wire y_da;
wire y_be;


mux_all dut (.a(a),.b(b),.s(s),.y_ga(y_ga),.y_da(y_da),.y_be(y_be));

initial begin
    $dumpfile ("mux_2x1.vcd");
    $dumpvars (0, mux_2x1_tb);

    $monitor("time t=%0t, a=%b, b=%b, s=%b | y_ga=%b,y_da=%b,y_be=%b", $time,a,b,s,y_ga,y_da,y_be);
    
    repeat(8) begin
    a = $random; #10;
    b = $random; #10;
    s = $random; #10;
end
end
endmodule

combinational/mux (2x1, 4x1 using 2x1, 16x1 using 4x1)/mux_2x1.vcd
$date
	Sat Mar 28 19:07:31 2026
$end
$version
	Icarus Verilog
$end
$timescale
	1s
$end
$scope module mux_2x1_tb $end
$var wire 1 ! y_ga $end
$var wire 1 " y_da $end
$var wire 1 # y_be $end
$var reg 1 $ a $end
$var reg 1 % b $end
$var reg 1 & s $end
$scope module dut $end
$var wire 1 $ a $end
$var wire 1 % b $end
$var wire 1 & s $end
$var wire 1 ! y_ga $end
$var wire 1 " y_da $end
$var wire 1 # y_be $end
$scope module m1 $end
$var wire 1 $ a $end
$var wire 1 % b $end
$var wire 1 & s $end
$var wire 1 ' w1 $end
$var wire 1 ( w2 $end
$var wire 1 ) w3 $end
$var wire 1 ! y $end
$upscope $end
$scope module m2 $end
$var wire 1 $ a $end
$var wire 1 % b $end
$var wire 1 & s $end
$var wire 1 * w1 $end
$var wire 1 + w2 $end
$var wire 1 , w3 $end
$var wire 1 " y $end
$upscope $end
$scope module m3 $end
$var wire 1 $ a $end
$var wire 1 % b $end
$var wire 1 & s $end
$var reg 1 - w1 $end
$var reg 1 . w2 $end
$var reg 1 / w3 $end
$var reg 1 # y $end
$upscope $end
$upscope $end
$upscope $end
$enddefinitions $end
$comment Show the parameter values. $end
$dumpall
$end
#0
$dumpvars
x/
0.
x-
x,
0+
x*
x)
0(
x'
x&
x%
0$
x#
x"
x!
$end
#10
1%
#20
1!
1"
0'
1)
0*
1,
1#
1/
0-
1&
#30
1$
#70
0!
0"
0)
0,
0#
0/
0%
#150
0$
#160
1!
1"
1)
1,
1#
1/
1%
#170
0!
0"
1'
0)
1*
0,
0#
0/
1-
0&
#180
1!
1"
1(
1+
1#
1.
1$
#220
0%
